{
  "sections": {
    "image_banner": {
      "type": "image-banner",
      "blocks": {
        "heading": {
          "type": "heading",
          "settings": {
            "heading": "Browse our latest products",
            "heading_size": "h0"
          }
        },
        "button": {
          "type": "buttons",
          "settings": {
            "button_label_1": "Shop all",
            "button_link_1": "shopify:\/\/collections\/all",
            "button_style_secondary_1": true,
            "button_label_2": "",
            "button_link_2": "",
            "button_style_secondary_2": false
          }
        }
      },
      "block_order": [
        "heading",
        "button"
      ],
      "settings": {
        "image_overlay_opacity": 40,
        "image_height": "large",
        "desktop_content_position": "bottom-center",
        "show_text_box": false,
        "desktop_content_alignment": "center",
        "color_scheme": "scheme-3",
        "image_behavior": "none",
        "mobile_content_alignment": "center",
        "stack_images_on_mobile": false,
        "show_text_below": false
      }
    },
    "feature_section_Q69PRk": {
      "type": "feature-section",
      "settings": {
        "selected_product_id": "gift-card",
        "feature_bullet_point_1": "Last long",
        "feature_bullet_point_2": "Affordable",
        "feature_bullet_point_3": "usable",
        "feature_bullet_point_4": "good product",
        "feature_bullet_point_5": "exclusive",
        "cta_button_link": "\/",
        "cta_button_text": "Shop Now"
      }
    },
    "featured_product_U34bzr": {
      "type": "featured-product",
      "blocks": {
        "text_UjrThQ": {
          "type": "text",
          "settings": {
            "text": "{{ section.settings.product.vendor }}",
            "text_style": "uppercase"
          }
        },
        "title_rmg7c8": {
          "type": "title",
          "settings": {
            "heading_size": "h1"
          }
        },
        "price_M4Xbph": {
          "type": "price",
          "settings": {
          }
        },
        "variant_picker_fWfH9W": {
          "type": "variant_picker",
          "settings": {
            "picker_type": "button",
            "swatch_shape": "circle"
          }
        },
        "quantity_selector_w4yFzd": {
          "type": "quantity_selector",
          "settings": {
          }
        },
        "buy_buttons_pKm6xb": {
          "type": "buy_buttons",
          "settings": {
            "show_dynamic_checkout": true,
            "show_gift_card_recipient": true
          }
        },
        "share_Cjymbt": {
          "type": "share",
          "settings": {
            "share_label": "Share"
          }
        }
      },
      "block_order": [
        "text_UjrThQ",
        "title_rmg7c8",
        "price_M4Xbph",
        "variant_picker_fWfH9W",
        "quantity_selector_w4yFzd",
        "buy_buttons_pKm6xb",
        "share_Cjymbt"
      ],
      "settings": {
        "product": "",
        "color_scheme": "",
        "secondary_background": false,
        "media_size": "medium",
        "constrain_to_viewport": true,
        "media_fit": "contain",
        "media_position": "left",
        "image_zoom": "lightbox",
        "hide_variants": false,
        "enable_video_looping": false,
        "padding_top": 36,
        "padding_bottom": 36
      }
    }
  },
  "order": [
    "image_banner",
    "feature_section_Q69PRk",
    "featured_product_U34bzr"
  ]
}